imgdisp/__init__.py
imgdisp/_version.py
rms_imgdisp-0.0.1.dist-info/LICENSE
rms_imgdisp-0.0.1.dist-info/METADATA
rms_imgdisp-0.0.1.dist-info/WHEEL
rms_imgdisp-0.0.1.dist-info/top_level.txt
rms_imgdisp-0.0.1.dist-info/RECORD
