Metadata-Version: 2.1
Name: rms-imgdisp
Version: 0.0.1
Summary: Module for displaying images
Maintainer-email: "Robert S. French" <rfrench@seti.org>
License: Apache-2.0
Project-URL: Homepage, https://github.com/SETI/rms-imgdisp
Project-URL: Repository, https://github.com/SETI/rms-imgdisp
Project-URL: Source, https://github.com/SETI/rms-imgdisp
Project-URL: Issues, https://github.com/SETI/rms-imgdisp/issues
Keywords: imgdisp
Classifier: Development Status :: 5 - Production/Stable
Classifier: Natural Language :: English
Classifier: Topic :: Scientific/Engineering
Classifier: Topic :: Scientific/Engineering :: Astronomy
Classifier: Topic :: Software Development :: Libraries :: Python Modules
Classifier: Topic :: Utilities
Classifier: License :: OSI Approved :: Apache Software License
Classifier: Programming Language :: Python :: 3.8
Classifier: Programming Language :: Python :: 3.9
Classifier: Programming Language :: Python :: 3.10
Classifier: Programming Language :: Python :: 3.11
Classifier: Programming Language :: Python :: 3.12
Classifier: Operating System :: MacOS :: MacOS X
Classifier: Operating System :: POSIX :: Linux
Classifier: Operating System :: Microsoft :: Windows
Requires-Python: >=3.8
License-File: LICENSE
Requires-Dist: numpy
Requires-Dist: Pillow
Requires-Dist: scipy
